Metadata-Version: 2.1
Name: wgit
Version: 0.0.3
Summary: A simple git wrapper to execute pre-commands and extensions
Home-page: https://github.com/DeGiorgiMarcello/git-wrapper
Author: Marcello De Giorgi
Author-email: degiorgimarcello@gmail.com
License-File: LICENSE.txt
Requires-Dist: pyyaml
